cdk_sqs_monitored/__init__.py
cdk_sqs_monitored/py.typed
cdk_sqs_monitored/_jsii/__init__.py
cdk_sqs_monitored/_jsii/cdk-sqs-monitored@1.0.3.jsii.tgz
cdk_sqs_monitored-1.0.3.dist-info/METADATA
cdk_sqs_monitored-1.0.3.dist-info/WHEEL
cdk_sqs_monitored-1.0.3.dist-info/top_level.txt
cdk_sqs_monitored-1.0.3.dist-info/RECORD
