Metadata-Version: 2.1
Name: cdk-sqs-monitored
Version: 1.0.3
Summary: AWS CDK SQS Construct with alarms and dead letter queue
Home-page: https://github.com/kamilbiela/cdk-sqs-monitored.git
Author: Kamil Biela<kamil.biela@gmail.com>
License: MIT
Project-URL: Source, https://github.com/kamilbiela/cdk-sqs-monitored.git
Platform: UNKNOWN
Classifier: Intended Audience :: Developers
Classifier: Operating System :: OS Independent
Classifier: Programming Language :: JavaScript
Classifier: Programming Language :: Python :: 3 :: Only
Classifier: Programming Language :: Python :: 3.6
Classifier: Programming Language :: Python :: 3.7
Classifier: Programming Language :: Python :: 3.8
Classifier: Typing :: Typed
Classifier: License :: OSI Approved
Requires-Python: >=3.6
Requires-Dist: jsii (~=1.2.0)
Requires-Dist: publication (>=0.0.3)
Requires-Dist: aws-cdk.aws-cloudwatch-actions (==1.32.2)
Requires-Dist: aws-cdk.aws-sns (==1.32.2)
Requires-Dist: aws-cdk.aws-sns-subscriptions (==1.32.2)
Requires-Dist: aws-cdk.aws-sqs (==1.32.2)
Requires-Dist: aws-cdk.core (==1.32.2)
Requires-Dist: constructs (==2.0.1)
